st_hierarchicalGrid/__init__.py
st_hierarchicalGrid/frontend/build/asset-manifest.json
st_hierarchicalGrid/frontend/build/bootstrap.min.css
st_hierarchicalGrid/frontend/build/index.html
st_hierarchicalGrid/frontend/build/static/js/239.f2189406.chunk.js
st_hierarchicalGrid/frontend/build/static/js/239.f2189406.chunk.js.LICENSE.txt
st_hierarchicalGrid/frontend/build/static/js/239.f2189406.chunk.js.map
st_hierarchicalGrid/frontend/build/static/js/732.c24ff1d5.chunk.js
st_hierarchicalGrid/frontend/build/static/js/732.c24ff1d5.chunk.js.map
st_hierarchicalGrid/frontend/build/static/js/977.2f56a4d3.chunk.js
st_hierarchicalGrid/frontend/build/static/js/977.2f56a4d3.chunk.js.LICENSE.txt
st_hierarchicalGrid/frontend/build/static/js/977.2f56a4d3.chunk.js.map
st_hierarchicalGrid/frontend/build/static/js/main.0fbdb6ae.js
st_hierarchicalGrid/frontend/build/static/js/main.0fbdb6ae.js.LICENSE.txt
st_hierarchicalGrid/frontend/build/static/js/main.0fbdb6ae.js.map
streamlit_hierarchical_grid-0.0.1.dist-info/licenses/LICENSE
streamlit_hierarchical_grid-0.0.1.dist-info/METADATA
streamlit_hierarchical_grid-0.0.1.dist-info/WHEEL
streamlit_hierarchical_grid-0.0.1.dist-info/top_level.txt
streamlit_hierarchical_grid-0.0.1.dist-info/RECORD
